{
  "$schema": "https://ui.shadcn.com/schema/registry-item.json",
  "name": "header",
  "type": "registry:component",
  "title": "Header Section",
  "description": "A responsive header component with navigation, branding, and optional features.",
  "dependencies": [
    "framer-motion"
  ],
  "registryDependencies": [
    "button",
    "input"
  ],
  "files": [
    {
      "path": "registry/default-style/blocks/header/header.tsx",
      "content": "'use client'\n\nimport Link from \"next/link\"\nimport { motion } from \"framer-motion\"\nimport { cn } from \"@/lib/utils\"\nimport { Button } from \"@/registry/default-style/ui/button\"\nimport { Input } from \"@/registry/default-style/ui/input\"\nimport { Menu, Search, User, ShoppingCart, X } from \"lucide-react\"\nimport * as React from \"react\" // For useState\n\ninterface NavLink {\n  label: string;\n  href: string;\n}\n\ninterface HeaderProps extends React.HTMLAttributes<HTMLDivElement> {\n  logoText: string;\n  logoHref: string;\n  navLinks?: NavLink[];\n  ctaButton?: {\n    label: string;\n    href: string;\n  };\n  variant?: \"simple\" | \"auth-search\" | \"centered-nav\";\n}\n\nconst containerVariants = {\n  hidden: { opacity: 0 },\n  visible: {\n    opacity: 1,\n    transition: {\n      staggerChildren: 0.1,\n    },\n  },\n};\n\nconst itemVariants = {\n  hidden: { opacity: 0, y: -20 },\n  visible: { opacity: 1, y: 0 },\n};\n\nconst mobileMenuVariants = {\n  hidden: { opacity: 0, y: -50 },\n  visible: { opacity: 1, y: 0, transition: { duration: 0.3 } },\n  exit: { opacity: 0, y: -50, transition: { duration: 0.3 } },\n};\n\nexport default function Header({\n  logoText,\n  logoHref,\n  navLinks,\n  ctaButton,\n  variant = \"simple\",\n  className,\n  ...props\n}: HeaderProps) {\n  const [isMobileMenuOpen, setIsMobileMenuOpen] = React.useState(false);\n\n  return (\n    // @ts-ignore\n    <motion.header\n      className={cn(\"w-full py-4 px-4 md:px-6 border-b\", className)}\n      initial=\"hidden\"\n      animate=\"visible\"\n      variants={containerVariants}\n      {...props}\n    >\n      <div className=\"container flex items-center justify-between h-14\">\n        <motion.div variants={itemVariants}>\n          <Link href={logoHref} className=\"text-xl font-bold\">\n            {logoText}\n          </Link>\n        </motion.div>\n\n        {variant === \"simple\" && (\n          <>\n            <motion.nav className=\"hidden md:flex gap-4 lg:gap-6\" variants={containerVariants}>\n              {navLinks?.map((link, index) => (\n                <motion.div key={index} variants={itemVariants}>\n                  <Link href={link.href} className=\"text-sm font-medium hover:underline underline-offset-4\">\n                    {link.label}\n                  </Link>\n                </motion.div>\n              ))}\n            </motion.nav>\n            <motion.div className=\"hidden md:block\" variants={itemVariants}>\n              {ctaButton && (\n                <Link href={ctaButton.href}>\n                  <Button size=\"sm\">{ctaButton.label}</Button>\n                </Link>\n              )}\n            </motion.div>\n            <motion.div variants={itemVariants}>\n              <Button\n                variant=\"outline\"\n                size=\"icon\"\n                className=\"md:hidden\"\n                onClick={() => setIsMobileMenuOpen(!isMobileMenuOpen)}\n              >\n                {isMobileMenuOpen ? <X className=\"h-5 w-5\" /> : <Menu className=\"h-5 w-5\" />}\n                <span className=\"sr-only\">Toggle mobile menu</span>\n              </Button>\n            </motion.div>\n          </>\n        )}\n\n        {variant === \"auth-search\" && (\n          <>\n            <motion.nav className=\"hidden md:flex flex-1 justify-center gap-4 lg:gap-6\" variants={containerVariants}>\n              {navLinks?.map((link, index) => (\n                <motion.div key={index} variants={itemVariants}>\n                  <Link href={link.href} className=\"text-sm font-medium hover:underline underline-offset-4\">\n                    {link.label}\n                  </Link>\n                </motion.div>\n              ))}\n            </motion.nav>\n            <motion.div className=\"hidden md:flex items-center gap-4\" variants={containerVariants}>\n              <motion.div variants={itemVariants}>\n                <Input type=\"search\" placeholder=\"Search...\" className=\"w-full max-w-xs\" />\n              </motion.div>\n              <motion.div variants={itemVariants}>\n                <Button variant=\"ghost\" size=\"icon\">\n                  <Search className=\"h-5 w-5\" />\n                  <span className=\"sr-only\">Search</span>\n                </Button>\n              </motion.div>\n              <motion.div variants={itemVariants}>\n                <Button variant=\"ghost\" size=\"icon\">\n                  <ShoppingCart className=\"h-5 w-5\" />\n                  <span className=\"sr-only\">Shopping Cart</span>\n                </Button>\n              </motion.div>\n              <motion.div variants={itemVariants}>\n                <Button variant=\"ghost\" size=\"icon\">\n                  <User className=\"h-5 w-5\" />\n                  <span className=\"sr-only\">User Profile</span>\n                </Button>\n              </motion.div>\n            </motion.div>\n            <motion.div variants={itemVariants}>\n              <Button\n                variant=\"outline\"\n                size=\"icon\"\n                className=\"md:hidden\"\n                onClick={() => setIsMobileMenuOpen(!isMobileMenuOpen)}\n              >\n                {isMobileMenuOpen ? <X className=\"h-5 w-5\" /> : <Menu className=\"h-5 w-5\" />}\n                <span className=\"sr-only\">Toggle mobile menu</span>\n              </Button>\n            </motion.div>\n          </>\n        )}\n\n        {variant === \"centered-nav\" && (\n          <>\n            <motion.div className=\"hidden md:flex flex-1 justify-end items-center gap-4 lg:gap-6\" variants={containerVariants}>\n              {navLinks?.slice(0, Math.ceil((navLinks?.length || 0) / 2)).map((link, index) => (\n                <motion.div key={index} variants={itemVariants}>\n                  <Link href={link.href} className=\"text-sm font-medium hover:underline underline-offset-4\">\n                    {link.label}\n                  </Link>\n                </motion.div>\n              ))}\n            </motion.div>\n            <motion.div className=\"hidden md:flex flex-1 justify-start items-center gap-4 lg:gap-6\" variants={containerVariants}>\n              {navLinks?.slice(Math.ceil((navLinks?.length || 0) / 2)).map((link, index) => (\n                <motion.div key={index} variants={itemVariants}>\n                  <Link href={link.href} className=\"text-sm font-medium hover:underline underline-offset-4\">\n                    {link.label}\n                  </Link>\n                </motion.div>\n              ))}\n            </motion.div>\n            <motion.div variants={itemVariants}>\n              <Button\n                variant=\"outline\"\n                size=\"icon\"\n                className=\"md:hidden\"\n                onClick={() => setIsMobileMenuOpen(!isMobileMenuOpen)}\n              >\n                {isMobileMenuOpen ? <X className=\"h-5 w-5\" /> : <Menu className=\"h-5 w-5\" />}\n                <span className=\"sr-only\">Toggle mobile menu</span>\n              </Button>\n            </motion.div>\n          </>\n        )}\n      </div>\n\n      {isMobileMenuOpen && (\n        <motion.div\n          className=\"md:hidden absolute top-14 left-0 w-full bg-background border-b z-20\"\n          initial=\"hidden\"\n          animate=\"visible\"\n          exit=\"exit\" // Use exit prop for AnimatePresence\n          variants={mobileMenuVariants}\n        >\n          <nav className=\"flex flex-col gap-2 p-4\">\n            {navLinks?.map((link, index) => (\n              <motion.div key={index} variants={itemVariants}>\n                <Link href={link.href} className=\"block px-3 py-2 text-base font-medium hover:bg-muted\" onClick={() => setIsMobileMenuOpen(false)}>\n                  {link.label}\n                </Link>\n              </motion.div>\n            ))}\n            {ctaButton && (\n                <motion.div variants={itemVariants}>\n                    <Link href={ctaButton.href} className=\"block px-3 py-2\">\n                        <Button className=\"w-full\" onClick={() => setIsMobileMenuOpen(false)}>{ctaButton.label}</Button>\n                    </Link>\n                </motion.div>\n            )}\n            {variant === \"auth-search\" && (\n                <>\n                    <motion.div className=\"px-3 py-2\" variants={itemVariants}>\n                        <Input type=\"search\" placeholder=\"Search...\" className=\"w-full\" />\n                    </motion.div>\n                    <motion.div className=\"flex justify-around py-2\" variants={containerVariants}>\n                        <motion.div variants={itemVariants}>\n                            <Button variant=\"ghost\" size=\"icon\" className=\"w-full\">\n                                <ShoppingCart className=\"h-5 w-5\" />\n                                <span className=\"sr-only\">Shopping Cart</span>\n                            </Button>\n                        </motion.div>\n                        <motion.div variants={itemVariants}>\n                            <Button variant=\"ghost\" size=\"icon\" className=\"w-full\">\n                                <User className=\"h-5 w-5\" />\n                                <span className=\"sr-only\">User Profile</span>\n                            </Button>\n                        </motion.div>\n                    </motion.div>\n                </>\n            )}\n          </nav>\n        </motion.div>\n      )}\n    </motion.header>\n  );\n}\n",
      "type": "registry:component"
    },
    {
      "path": "registry/default-style/blocks/header/mock-data.ts",
      "content": "import { Menu, Search, User, ShoppingCart } from \"lucide-react\";\n\nexport const mockHeaderData = {\n  navLinks: [\n    { label: \"Home\", href: \"/\" },\n    { label: \"Products\", href: \"/products\" },\n    { label: \"Services\", href: \"/services\" },\n    { label: \"About\", href: \"/about\" },\n    { label: \"Contact\", href: \"/contact\" },\n  ],\n  ctaButton: {\n    label: \"Get Started\",\n    href: \"/signup\",\n  },\n  simpleHeader: {\n    logoText: \"MyBrand\",\n    logoHref: \"/\",\n    variant: \"simple\" as const,\n  },\n  authSearchHeader: {\n    logoText: \"MyStore\",\n    logoHref: \"/\",\n    variant: \"auth-search\" as const,\n  },\n  centeredNavHeader: {\n    logoText: \"MyWebsite\",\n    logoHref: \"/\",\n    variant: \"centered-nav\" as const,\n  },\n};\n",
      "type": "registry:lib"
    }
  ]
}